pandb/__init__.py
pandb/base/__init__.py
pandb/base/dbapi2.py
pandb/core/__init__.py
pandb/core/cursor.py
pandb/core/dtype.py
pandb/core/parser.py
pandb/core/record.py
pandb/core/table.py
pandb/proxy/__init__.py
pandb/proxy/csv.py
pandb/proxy/excel.py
pandb/proxy/sql.py
pandb-0.1.11.dist-info/LICENSE
pandb-0.1.11.dist-info/METADATA
pandb-0.1.11.dist-info/WHEEL
pandb-0.1.11.dist-info/top_level.txt
pandb-0.1.11.dist-info/RECORD
